{
    "Version": "2012-10-17",
    "Statement": [
        {
            "Sid": "EKSFullAccess",
            "Effect": "Allow",
            "Action": "eks:*",
            "Resource": "*"
        },
        {
            "Sid": "IAM",
            "Effect": "Allow",
            "Action": [
                "iam:CreateInstanceProfile",
                "iam:DeleteInstanceProfile",
                "iam:GetRole",
                "iam:GetInstanceProfile",
                "iam:RemoveRoleFromInstanceProfile",
                "iam:CreateRole",
                "iam:DeleteRole",
                "iam:AttachRolePolicy",
                "iam:PutRolePolicy",
                "iam:AddRoleToInstanceProfile",
                "iam:PassRole",
                "iam:DetachRolePolicy",
                "iam:DeleteRolePolicy",
                "iam:GetRolePolicy",
                "iam:ListRoles",
                "iam:CreateServiceLinkedRole"
            ],
            "Resource": "*"
        },
        {
            "Sid": "AWSConsole",
            "Effect": "Allow",
            "Action": [
                "iam:ListRoles",
                "iam:ListAttachedRolePolicies",
                "ec2:DescribeSecurityGroups",
                "ec2:DescribeSubnets",
                "ec2:DescribeVpcs",
                "ec2:DescribeKeyPairs"
            ],
            "Resource": "*"
        }
    ]
}